Questgen/__init__.py
Questgen/main.py
Questgen/encoding/__init__.py
Questgen/encoding/encoding.py
Questgen/mcq/__init__.py
Questgen/mcq/mcq.py
cogexquestgen-1.0.3.dist-info/LICENSE
cogexquestgen-1.0.3.dist-info/METADATA
cogexquestgen-1.0.3.dist-info/WHEEL
cogexquestgen-1.0.3.dist-info/top_level.txt
cogexquestgen-1.0.3.dist-info/RECORD
