Metadata-Version: 2.1
Name: cogexquestgen
Version: 1.0.3
Summary: Question generator from any text
Home-page: https://github.com/JeffMII/Questgen.ai
Author: Forked Questgen Contributor: Jeff Myers
Author-email: j3f9y.f@gmail.com
License: UNKNOWN
Platform: UNKNOWN
License-File: LICENSE
Requires-Dist: torch (==1.9.0)
Requires-Dist: transformers (<=4.2.2,>=3.0.2)
Requires-Dist: pytorch-lightning (<=0.8.4,>=0.8.1)
Requires-Dist: sense2vec (==2.0.0)
Requires-Dist: strsim (==0.0.3)
Requires-Dist: six (<=1.16.0,>=1.15.0)
Requires-Dist: networkx (<=2.6.3,>=2.4.0)
Requires-Dist: numpy (==1.16.3)
Requires-Dist: scipy (<=1.5.4,>=1.4.1)
Requires-Dist: scikit-learn (<=1.0.2,>=0.22.1)
Requires-Dist: unidecode (<=1.3.2,>=1.1.1)
Requires-Dist: future (==0.18.2)
Requires-Dist: joblib (<=1.1.0,>=0.14.1)
Requires-Dist: spacy (<=3.2.1,>=3.0.0)
Requires-Dist: pytz (<=2021.3,>=2020.1)
Requires-Dist: python-dateutil (<=2.8.2,>=2.8.1)
Requires-Dist: boto3 (<=1.20.39,>=1.14.40)
Requires-Dist: flashtext (==2.7)
Requires-Dist: pandas (<=1.1.5,>=1.1.1)
Requires-Dist: nltk (==3.6.3)
Requires-Dist: cogexpke (==1.8.1)
